Workbook

Sheet W2_Income
A1: W-2 INCOME – SIMPLE TAX ORGANIZER (NOT AN OFFICIAL IRS FORM)
A2: Audience: Typical 9-to-5 employees with wages reported on W-2s and minor interest/dividend income.
A3: If you have self-employment, rentals, K-1s, crypto, heavy trading, or complex items, use real tax software or a tax professional.
A4: Use this sheet only to total your W-2 information and transfer it to IRS Form 1040 for Tax Year 2025.
A5: Row 7 contains SAMPLE data. Delete that row before entering your real information.
A6: Employer | B6: Employee Name | C6: Wages (Box 1) | D6: Federal Tax Withheld (Box 2) | E6: SS Wages (Box 3) | F6: SS Tax Withheld (Box 4) | G6: Medicare Wages (Box 5) | H6: Medicare Tax Withheld (Box 6)
A7: SampleCo Inc. | B7: John Sample | C7: 60000 | D7: 5000 | E7: 60000 | F7: 3720 | G7: 60000 | H7: 870
A100: Totals | C100: =SUM(C8:C99) | D100: =SUM(D8:D99) | E100: =SUM(E8:E99) | F100: =SUM(F8:F99) | G100: =SUM(G8:G99) | H100: =SUM(H8:H99)

Sheet 1099_And_Other
A1: Simple organizer for 1099 interest/dividends/other. Not for complex trading, large self-employment, or rentals.
A2: If you had stock sales, crypto, options, significant self-employment (1099-NEC), or rental income, use proper tax software or a CPA.
A3: Row 7 contains SAMPLE data. Delete that row before entering your real information.
A6: Source (Bank/Broker/Payer) | B6: Form Type (1099-INT, 1099-DIV, etc.) | C6: Income Type (Taxable interest, Ordinary dividends, etc.) | D6: Amount | E6: Federal Tax Withheld | F6: Notes
A7: Sample Bank | B7: 1099-INT | C7: Taxable interest | D7: 200 | E7: 0 | F7: Sample interest
A102: Total Taxable Interest | B102: =SUMIF(C8:C99,"Taxable interest",D8:D99)
A103: Total Ordinary Dividends | B103: =SUMIF(C8:C99,"Ordinary dividends",D8:D99)
A104: Total Qualified Dividends | B104: =SUMIF(C8:C99,"Qualified dividends",D8:D99)
A105: Total Capital Gain Distributions | B105: =SUMIF(C8:C99,"Capital gain distributions",D8:D99)
A106: Total Other Income | B106: =SUMIF(C8:C99,"Other income",D8:D99)
A108: Total Federal Tax Withheld (All 1099s) | B108: =SUM(E8:E99)

Sheet Itemized_Deductions
A1: ITEMIZED DEDUCTIONS (OPTIONAL)
A2: Most taxpayers use the STANDARD DEDUCTION. Only fill this out if your deductions may exceed the standard.
A3: For 2025 approx: Single/MFS 14,900; MFJ 29,800; HOH 22,400 (confirm with IRS Form 1040 Instructions).
A4: Sample rows are provided. Delete them before entering your real information.
A6: Date | B6: Organization | C6: Type (Cash/Goods) | D6: Amount | E6: Notes
A7: 2025-03-15 | B7: Sample Charity | C7: Cash | D7: 500 | E7: Sample donation
A30: Total Charitable Donations | B30: =SUM(D8:D29)
A33: Mortgage Lender | B33: Mortgage Interest Paid | C33: Notes
A34: Sample Bank Mortgage | B34: 8000 | C34: Sample interest
A46: Total Mortgage Interest | B46: =SUM(B35:B45)
A47: Other SALT (optional): Enter other deductible state/local taxes such as vehicle registration tax based on car value or local income taxes. Do NOT enter sales tax, flat DMV fees, or utility bills. Most taxpayers will leave this blank.
A49: State Income Tax Paid | B49: Property Tax Paid | C49: Other SALT
A50: 2000 | B50: 3000 | C50: 0
A53: Total SALT Entered | B53: =SUM(A51:C52)
A56: Date | B56: Provider | C56: Amount | D56: Notes
A57: 2025-06-01 | B57: Sample Clinic | C57: 1000 | D57: Sample expense
A79: Total Medical Expenses | B79: =SUM(C58:C78)

Sheet Summary_1040_Helper
A1: Summary helper for 2025 Form 1040 (simple return). Not a substitute for the actual IRS form.
A2: START HERE after entering your income: this sheet shows totals you will copy to Form 1040.
A3: Income Summary (values below map to 2025 Form 1040 lines):
A5: Total W-2 Wages (1040 line 1) | B5: =W2_Income!C100
A6: Taxable Interest (1040 line 2b) | B6: =1099_And_Other!B102
A7: Ordinary Dividends (1040 line 3b) | B7: =1099_And_Other!B103
A8: Qualified Dividends (1040 line 3a - info only) | B8: =1099_And_Other!B104
A9: Capital Gain Distributions (simple) (1040 line 7) | B9: =1099_And_Other!B105
A10: Other Income (simple, via Schedule 1 → 1040 line 8) | B10: =1099_And_Other!B106
A12: Total Income (approx) (1040 line 9) | B12: =B5+B6+B7+B9+B10
A15: Filing Status | B15: Single
A16: Standard Deduction for 2025 (auto from filing status) | B16: =IF(B15="Single",14900,IF(B15="Married Filing Separately",14900,IF(B15="Married Filing Jointly",29800,IF(B15="Head of Household",22400,""))))
A18: Taxable Income (1040 line 15, rough) | B18: =MAX(B12-B34,0)
A21: W-2 Federal Tax Withheld (1040 line 25a) | B21: =W2_Income!D100
A22: 1099 Federal Tax Withheld (1040 line 25b) | B22: =1099_And_Other!B108
A23: Total Federal Tax Withheld (1040 line 25d) | B23: =B21+B22
A25: Charitable Donations | B25: =Itemized_Deductions!B30
A26: Mortgage Interest | B26: =Itemized_Deductions!B46
A27: SALT Entered | B27: =Itemized_Deductions!B53
A28: SALT Deduction (max 10,000) | B28: =MIN(10000,B27)
A29: Medical Expenses Entered | B29: =Itemized_Deductions!B79
A30: Allowed Medical Deduction (>7.5% of income) | B30: =MAX(0,B29-(B12*0.075))
A32: Total Itemized Deductions | B32: =B25+B26+B28+B30
A34: Deduction Used (Standard vs Itemized, larger is used) | B34: =IF(B32>B16,B32,B16)

Sheet Filing_Instructions
A1: HOW TO USE THIS SHEET FOR YOUR 2025 TAXES (FILED IN 2026)
A2: Version 1.0 – For Tax Year 2025 only.
A3: START HERE:
A4: 1) Go to W2_Income and enter each W-2 (delete sample row first).
A5: 2) Go to 1099_And_Other and enter any 1099-INT/DIV/etc. (delete sample row first).
A6: 3) (Optional) Go to Itemized_Deductions if you have mortgage, large donations, taxes, or medical expenses.
A7: 4) Come to Summary_1040_Helper to see totals. The sheet automatically chooses Standard vs Itemized deduction.
A8: 5) Use the mapping table below to copy numbers to the official 2025 Form 1040.
A10: FILING OPTIONS:
A11: E-FILE (RECOMMENDED): Use IRS Free File or reputable tax software and enter the values from Summary_1040_Helper.
A12: PAPER FILE: Download 2025 Form 1040 from IRS.gov/Form1040, print, and copy values manually.
A14: Mailing addresses for Utah (verify each year at IRS.gov 'Where to file Form 1040'):
... A30: This spreadsheet is an unofficial helper. You are responsible for checking your return and following IRS instructions or consulting a tax professional.
A33: Spreadsheet Value (live link) | B33: Description | C33: 2025 Form 1040 Line
A34: =Summary_1040_Helper!B5 | B34: Total W-2 wages | C34: Line 1
A35: =Summary_1040_Helper!B6 | B35: Taxable interest | C35: Line 2b
A36: =Summary_1040_Helper!B7 | B36: Ordinary dividends | C36: Line 3b
A37: =Summary_1040_Helper!B8 | B37: Qualified dividends | C37: Line 3a
A38: =Summary_1040_Helper!B9 | B38: Capital gain distributions (simple) | C38: Line 7
A39: =Summary_1040_Helper!B10 | B39: Other income (simple) | C39: Line 8
A40: =Summary_1040_Helper!B12 | B40: Total income (approx) | C40: Line 9
A41: =Summary_1040_Helper!B16 | B41: Standard deduction (from filing status) | C41: Line 12 (Std ded)
A42: =Summary_1040_Helper!B32 | B42: Total itemized deductions | C42: Schedule A total
A43: =Summary_1040_Helper!B34 | B43: Deduction used (Std vs Itemized) | C43: Line 12 (Deduction used)
A44: =Summary_1040_Helper!B18 | B44: Taxable income (rough) | C44: Line 15
A45: =Summary_1040_Helper!B21 | B45: W-2 federal tax withheld | C45: Line 25a
A46: =Summary_1040_Helper!B22 | B46: 1099 federal tax withheld | C46: Line 25b
A47: =Summary_1040_Helper!B23 | B47: Total federal tax withheld | C47: Line 25d
